odoo9_addon_partner_address_street3-9.0.1.1.0-py2.7-nspkg.pth
odoo9_addon_partner_address_street3-9.0.1.1.0.dist-info/top_level.txt
odoo9_addon_partner_address_street3-9.0.1.1.0.dist-info/WHEEL
odoo9_addon_partner_address_street3-9.0.1.1.0.dist-info/RECORD
odoo9_addon_partner_address_street3-9.0.1.1.0.dist-info/metadata.json
odoo9_addon_partner_address_street3-9.0.1.1.0.dist-info/DESCRIPTION.rst
odoo9_addon_partner_address_street3-9.0.1.1.0.dist-info/METADATA
odoo9_addon_partner_address_street3-9.0.1.1.0.dist-info/namespace_packages.txt
odoo_addons/partner_address_street3/__openerp__.py
odoo_addons/partner_address_street3/hooks.py
odoo_addons/partner_address_street3/__init__.py
odoo_addons/partner_address_street3/README.rst
odoo_addons/partner_address_street3/view/partner_view.xml
odoo_addons/partner_address_street3/models/partner.py
odoo_addons/partner_address_street3/models/__init__.py
odoo_addons/partner_address_street3/models/res_country.py
odoo_addons/partner_address_street3/i18n/it.po
odoo_addons/partner_address_street3/i18n/es.po
odoo_addons/partner_address_street3/i18n/hr.po
odoo_addons/partner_address_street3/i18n/bg.po
odoo_addons/partner_address_street3/i18n/sl.po
odoo_addons/partner_address_street3/i18n/da.po
odoo_addons/partner_address_street3/i18n/nl.po
odoo_addons/partner_address_street3/i18n/de.po
odoo_addons/partner_address_street3/i18n/fr.po
odoo_addons/partner_address_street3/i18n/pt_BR.po
odoo_addons/partner_address_street3/i18n/fi.po
odoo_addons/partner_address_street3/i18n/hr_HR.po
odoo_addons/partner_address_street3/tests/__init__.py
odoo_addons/partner_address_street3/tests/test_street_3.py
odoo_addons/partner_address_street3/static/description/icon.png
