Metadata-Version: 2.0
Name: odoo9-addon-partner-address-street3
Version: 9.0.1.1.0
Summary: Street3 in addresses
Home-page: http://www.camptocamp.com
Author: UNKNOWN
Author-email: UNKNOWN
License: AGPL-3
Platform: UNKNOWN
Requires-Dist: odoo (<9.1a,>=9.0a)
Classifier: Programming Language :: Python :: 2.7
Classifier: Framework :: Odoo
Classifier: License :: OSI Approved :: GNU Affero General Public License v3
